Waila/__init__.py
Waila/waila.py
Waila-0.1.1.dist-info/LICENSE
Waila-0.1.1.dist-info/METADATA
Waila-0.1.1.dist-info/WHEEL
Waila-0.1.1.dist-info/top_level.txt
Waila-0.1.1.dist-info/RECORD
