Metadata-Version: 2.1
Name: Waila
Version: 0.1.1
Summary: Quickly find documentation
Home-page: https://github.com/AsgerJon
Author: Asger Jon Vistisen
Author-email: asgerjon2@gmail.com
Classifier: Programming Language :: Python :: 3
Classifier: License :: OSI Approved :: MIT License
Classifier: Operating System :: OS Independent
Requires-Python: >=3.6
License-File: LICENSE
